ucb_api/__init__.py
ucb_api/__main__.py
ucb_api/api/__init__.py
ucb_api/api/buildtargets_api.py
ucb_api/api_client.py
ucb_api/configuration.py
ucb_api/main.py
ucb_api/models/__init__.py
ucb_api/models/inline_build_target.py
ucb_api/python_client/.gitignore
ucb_api/python_client/.swagger-codegen/VERSION
ucb_api/python_client/.swagger-codegen-ignore
ucb_api/python_client/.travis.yml
ucb_api/python_client/__init__.py
ucb_api/python_client/docs/BuildsApi.md
ucb_api/python_client/docs/BuildtargetsApi.md
ucb_api/python_client/docs/ConfigApi.md
ucb_api/python_client/docs/CredentialsApi.md
ucb_api/python_client/docs/InlineResponse200.md
ucb_api/python_client/docs/InlineResponse2001.md
ucb_api/python_client/docs/InlineResponse20010.md
ucb_api/python_client/docs/InlineResponse20011.md
ucb_api/python_client/docs/InlineResponse20012.md
ucb_api/python_client/docs/InlineResponse2002.md
ucb_api/python_client/docs/InlineResponse2003.md
ucb_api/python_client/docs/InlineResponse2004.md
ucb_api/python_client/docs/InlineResponse2005.md
ucb_api/python_client/docs/InlineResponse2006.md
ucb_api/python_client/docs/InlineResponse2007.md
ucb_api/python_client/docs/InlineResponse2008.md
ucb_api/python_client/docs/InlineResponse2009.md
ucb_api/python_client/docs/Options.md
ucb_api/python_client/docs/Options1.md
ucb_api/python_client/docs/Options10.md
ucb_api/python_client/docs/Options2.md
ucb_api/python_client/docs/Options3.md
ucb_api/python_client/docs/Options4.md
ucb_api/python_client/docs/Options5.md
ucb_api/python_client/docs/Options6.md
ucb_api/python_client/docs/Options7.md
ucb_api/python_client/docs/Options8.md
ucb_api/python_client/docs/Options9.md
ucb_api/python_client/docs/OrgsApi.md
ucb_api/python_client/docs/OrgsorgidcredentialssigningandroidKeystore.md
ucb_api/python_client/docs/OrgsorgidcredentialssigningiosProvisioningProfile.md
ucb_api/python_client/docs/OrgsorgidcredentialssigningosxCertificate.md
ucb_api/python_client/docs/OrgsorgidprojectsprojectidartifactsdeleteBuilds.md
ucb_api-0.1.1.dist-info/entry_points.txt
ucb_api-0.1.1.dist-info/LICENSE
ucb_api-0.1.1.dist-info/WHEEL
ucb_api-0.1.1.dist-info/METADATA
ucb_api-0.1.1.dist-info/RECORD
