Metadata-Version: 2.1
Name: ucb-api
Version: 0.1.1
Summary: Python package for Unity Cloud Build api
Author: leynier
Author-email: leynier41@gmail.com
Requires-Python: >=3.7,<4.0
Classifier: Programming Language :: Python :: 3
Classifier: Programming Language :: Python :: 3.7
Classifier: Programming Language :: Python :: 3.8
Requires-Dist: certifi (>=2020.6.20,<2021.0.0)
Requires-Dist: pylint (>=2.6.0,<3.0.0)
Requires-Dist: python_dateutil (>=2.8.1,<3.0.0)
Requires-Dist: six (>=1.15.0,<2.0.0)
Requires-Dist: typer[all] (>=0.3.2,<0.4.0)
Requires-Dist: urllib3 (>=1.25.10,<2.0.0)
